ShiyanlouHtml5JiaochengHeji20160904/README.md
ShiyanlouHtml5JiaochengHeji20160904/__init__.py
ShiyanlouHtml5JiaochengHeji20160904/__main__.py
ShiyanlouHtml5JiaochengHeji20160904/file.epub
ShiyanlouHtml5JiaochengHeji20160904/index.html
ShiyanlouHtml5JiaochengHeji20160904/css/__init__.py
ShiyanlouHtml5JiaochengHeji20160904/css/annotations.css
ShiyanlouHtml5JiaochengHeji20160904/css/main.css
ShiyanlouHtml5JiaochengHeji20160904/css/normalize.css
ShiyanlouHtml5JiaochengHeji20160904/css/popup.css
ShiyanlouHtml5JiaochengHeji20160904/font/__init__.py
ShiyanlouHtml5JiaochengHeji20160904/font/fontello.eot
ShiyanlouHtml5JiaochengHeji20160904/font/fontello.svg
ShiyanlouHtml5JiaochengHeji20160904/font/fontello.ttf
ShiyanlouHtml5JiaochengHeji20160904/font/fontello.woff
ShiyanlouHtml5JiaochengHeji20160904/img/__init__.py
ShiyanlouHtml5JiaochengHeji20160904/img/annotator-glyph-sprite.png
ShiyanlouHtml5JiaochengHeji20160904/img/annotator-icon-sprite.png
ShiyanlouHtml5JiaochengHeji20160904/img/apple-touch-icon.png
ShiyanlouHtml5JiaochengHeji20160904/img/cancelfullscreen.png
ShiyanlouHtml5JiaochengHeji20160904/img/close.png
ShiyanlouHtml5JiaochengHeji20160904/img/fullscreen.png
ShiyanlouHtml5JiaochengHeji20160904/img/loader.gif
ShiyanlouHtml5JiaochengHeji20160904/img/menu-icon.png
ShiyanlouHtml5JiaochengHeji20160904/img/save.png
ShiyanlouHtml5JiaochengHeji20160904/img/saved.png
ShiyanlouHtml5JiaochengHeji20160904/img/settings-s.png
ShiyanlouHtml5JiaochengHeji20160904/img/settings.png
ShiyanlouHtml5JiaochengHeji20160904/img/star.png
ShiyanlouHtml5JiaochengHeji20160904/js/__init__.py
ShiyanlouHtml5JiaochengHeji20160904/js/epub.js
ShiyanlouHtml5JiaochengHeji20160904/js/epub.min.js
ShiyanlouHtml5JiaochengHeji20160904/js/epub.min.map
ShiyanlouHtml5JiaochengHeji20160904/js/hooks.min.js
ShiyanlouHtml5JiaochengHeji20160904/js/hooks.min.map
ShiyanlouHtml5JiaochengHeji20160904/js/reader.js
ShiyanlouHtml5JiaochengHeji20160904/js/reader.js.map
ShiyanlouHtml5JiaochengHeji20160904/js/reader.min.js
shiyanlou_html5_jiaocheng_heji_20160904-2024.3.2.0.dist-info/METADATA
shiyanlou_html5_jiaocheng_heji_20160904-2024.3.2.0.dist-info/WHEEL
shiyanlou_html5_jiaocheng_heji_20160904-2024.3.2.0.dist-info/entry_points.txt
shiyanlou_html5_jiaocheng_heji_20160904-2024.3.2.0.dist-info/top_level.txt
shiyanlou_html5_jiaocheng_heji_20160904-2024.3.2.0.dist-info/RECORD
